MANIFEST.in
README.rst
setup.py
bugzscout/__init__.py
bugzscout/client.py
bugzscout.egg-info/PKG-INFO
bugzscout.egg-info/SOURCES.txt
bugzscout.egg-info/dependency_links.txt
bugzscout.egg-info/entry_points.txt
bugzscout.egg-info/requires.txt
bugzscout.egg-info/top_level.txt
bugzscout/ext/__init__.py
bugzscout/ext/celery_app.py
bugzscout/ext/cli.py
test/test_client.py