Metadata-Version: 1.1
Name: bugzscout
Version: 0.0.1
Summary: Python interface for the FogBugz BugzScout API.
Home-page: https://github.com/thomasvandoren/bugzscout-py
Author: Thomas Van Doren
Author-email: thomas@thomasvandoren.com
License: BSD
Keywords: BugzScout,FogBugz
Platform: UNKNOWN
Classifier: Development Status :: 3 - Alpha
Classifier: Intended Audience :: Developers
Classifier: License :: OSI Approved :: BSD License
Classifier: Operating System :: OS Independent
Classifier: Programming Language :: Python
Classifier: Programming Language :: Python :: 2.6
Classifier: Programming Language :: Python :: 2.7
Classifier: Programming Language :: Python :: 3.1
Classifier: Programming Language :: Python :: 3.2
Classifier: Programming Language :: Python :: 3.3
Classifier: Programming Language :: Python :: Implementation :: PyPy
